oszitrace/_version.py
oszitrace/agilent.py
oszitrace/app.py
oszitrace/debug.py
oszitrace/dialogue.py
oszitrace/ioc.py
oszitrace/iocapp.py
oszitrace/iocmain.py
oszitrace/lecroy.py
oszitrace/sim.py
oszitrace/trace.py
oszitrace/display/waveform.py
oszitrace_ioc-0.2.0.dist-info/LICENSE
oszitrace_ioc-0.2.0.dist-info/METADATA
oszitrace_ioc-0.2.0.dist-info/WHEEL
oszitrace_ioc-0.2.0.dist-info/entry_points.txt
oszitrace_ioc-0.2.0.dist-info/top_level.txt
oszitrace_ioc-0.2.0.dist-info/RECORD
