Metadata-Version: 2.1
Name: oszitrace-ioc
Version: 0.2.0
Summary: Quick'n dirty view / save utility to retrieve and store waveforms from SCPI compliant devices
Author-email: Florin Boariu <florin.pt@rootshell.ro>, Matthias Rössle <matthias.roessle@helmholtz-berlin.de>
Project-URL: Source Code, https://gitlab.com/kmc3-xpp/oszitrace
Classifier: Programming Language :: Python :: 3
Classifier: License :: OSI Approved :: GNU General Public License v3 or later (GPLv3+)
Classifier: Operating System :: POSIX :: Linux
Classifier: Development Status :: 2 - Pre-Alpha
Classifier: Environment :: Console
Classifier: Intended Audience :: Science/Research
Classifier: Topic :: Scientific/Engineering
Requires-Python: >=3.8
License-File: LICENSE
Requires-Dist: caproto
Requires-Dist: xarray
Requires-Dist: numpy
Requires-Dist: parse
Requires-Dist: pyyaml
Provides-Extra: agilent
Requires-Dist: pyvisa ; extra == 'agilent'
Requires-Dist: pyvisa-py ; extra == 'agilent'
Provides-Extra: all
Requires-Dist: matplotlib ; extra == 'all'
Requires-Dist: emmi ; extra == 'all'
Requires-Dist: zarr ; extra == 'all'
Requires-Dist: h5netcdf ; extra == 'all'
Requires-Dist: pyvisa ; extra == 'all'
Requires-Dist: pyvicp ; extra == 'all'
Requires-Dist: pyvisa-py ; extra == 'all'
Provides-Extra: display
Requires-Dist: matplotlib ; extra == 'display'
Requires-Dist: emmi ; extra == 'display'
Requires-Dist: zarr ; extra == 'display'
Requires-Dist: h5netcdf ; extra == 'display'
Provides-Extra: lecroy
Requires-Dist: pyvisa ; extra == 'lecroy'
Requires-Dist: pyvicp ; extra == 'lecroy'
Requires-Dist: pyvisa-py ; extra == 'lecroy'
Provides-Extra: test
Requires-Dist: pytest ; extra == 'test'
Requires-Dist: pytest-cov ; extra == 'test'
Requires-Dist: pytest-asyncio ; extra == 'test'
